rlhf_utils/__init__.py
rlhf_utils/online_server/__init__.py
rlhf_utils/online_server/api_utils.py
rlhf_utils-0.1.1.dist-info/licenses/LICENSE
rlhf_utils-0.1.1.dist-info/METADATA
rlhf_utils-0.1.1.dist-info/WHEEL
rlhf_utils-0.1.1.dist-info/top_level.txt
rlhf_utils-0.1.1.dist-info/RECORD
