Metadata-Version: 2.4
Name: rlhf-utils
Version: 0.1.1
Summary: Efficient utilities for working with Large Language Models
Author-email: LLM Researcher <your.email@example.com>
License: MIT
Project-URL: Homepage, https://github.com/yourusername/rlhf-utils
Project-URL: Documentation, https://github.com/yourusername/rlhf-utils#readme
Project-URL: Bug Tracker, https://github.com/yourusername/rlhf-utils/issues
Project-URL: Source Code, https://github.com/yourusername/rlhf-utils
Keywords: llm,rlhf,ai,openai,gpt,parallel,utility
Classifier: Programming Language :: Python :: 3
Classifier: Programming Language :: Python :: 3.7
Classifier: Programming Language :: Python :: 3.8
Classifier: Programming Language :: Python :: 3.9
Classifier: Programming Language :: Python :: 3.10
Classifier: License :: OSI Approved :: MIT License
Classifier: Operating System :: OS Independent
Classifier: Intended Audience :: Science/Research
Classifier: Intended Audience :: Developers
Classifier: Topic :: Scientific/Engineering :: Artificial Intelligence
Classifier: Development Status :: 4 - Beta
Requires-Python: >=3.7
License-File: LICENSE
Requires-Dist: openai>=1.0.0
Requires-Dist: datasets>=2.0.0
Requires-Dist: tqdm>=4.45.0
Dynamic: license-file
